{
  "hash": "d074cf1fba7333435586c4e47cdc179b",
  "result": {
    "engine": "knitr",
    "markdown": "---\ntitle: \"Loading Your First Dataset\"\n---\n\n\n\nYour workspace is set up and your raw data is sitting in `data/raw/`.\nTime to write your first R code.\n\n## Packages\n\nR ships with a base set of tools. On top of that, the community has built\nthousands of *packages* — collections of ready-made code you can install\nand use without writing everything yourself. These are distributed through\n**CRAN** (the Comprehensive R Archive Network), R's official package\nrepository.\n\nThe family of packages we'll lean on most is called the **tidyverse** —\na curated set of tools that share a common design and work well together.\nWe'll introduce them one at a time. This chapter uses three of them plus\na few helpers for reading, writing, and navigating files.\n\n### Installing Packages\n\n\n::: {.cell}\n\n```{.r .cell-code}\n# Run this once to install the packages onto your computer.\ninstall.packages(c(\n  \"dplyr\", # for manipulating data\n  \"readr\", # for reading common data files\n  \"fs\", # for working with files and paths\n  \"here\" # for building paths that work everywhere\n))\n```\n:::\n\n\n## Reading Data Files\n\n### Reading our Comma Delimited File (.csv)\n\nWe are going to do a few things here:\n\n1. Load the packages we need into our session.\n2. Build a path to our data file and save it as `csv_path`.\n3. Read the data into our session and save it as `covid_data`.\n\n\n::: {.cell}\n\n```{.r .cell-code}\nlibrary(dplyr)\nlibrary(readr)\nlibrary(fs)\nlibrary(here)\n```\n:::\n\n\n### Paths and `here()`\n\nBefore reading the file, a word on paths — because this is where R trips\npeople up early.\n\nWhen you run code interactively, R looks for files starting from your project\nroot (wherever your `.Rproj` file lives). When Quarto *renders* a document,\nit shifts the working directory to wherever the `.qmd` file lives. These\nlocations are often different, which is why a path that works in your console\ncan fail during render, or vice versa.\n\n`here()` from the `here` package fixes this. It detects your project root\nand always builds paths from there, regardless of how or where the code runs.\nUse it instead of `path()` whenever you are building paths to data files.\n\n\n::: {.cell}\n\n```{.r .cell-code}\n# here() takes folder names as separate arguments.\n# It joins them with the correct separator for your OS.\ncsv_path <- here(\"data\", \"raw\", \"ct_covid_by_town_2026-06-30.csv\")\n\ncovid_data <- read_csv(csv_path)\n```\n:::\n\n\n\n\nWe have our data saved into our session — now let's look at it.\n\n\n::: {.cell}\n\n```{.r .cell-code}\n# taking a look at the top few rows\nhead(covid_data)\n```\n\n::: {.cell-output .cell-output-stdout}\n\n```\n# A tibble: 6 × 16\n  `Last update date` `Town number` Town         `Total cases` `Confirmed cases`\n  <chr>                      <dbl> <chr>                <dbl>             <dbl>\n1 06/24/2022                     1 Andover                514               439\n2 06/24/2022                     2 Ansonia               4911              4222\n3 06/24/2022                     3 Ashford                744               671\n4 06/24/2022                     4 Avon                  3030              2773\n5 06/24/2022                     5 Barkhamsted            527               490\n6 06/24/2022                     6 Beacon Falls          1306              1163\n# ℹ 11 more variables: `Probable cases` <dbl>, `Case rate` <dbl>,\n#   `Total deaths` <dbl>, `Confirmed deaths` <dbl>, `Probable deaths` <dbl>,\n#   `People tested` <dbl>, `Rate tested per 100k` <dbl>,\n#   `Number of tests` <dbl>, `Number of positives` <dbl>,\n#   `Number of negatives` <dbl>, `Number of indeterminates` <dbl>\n```\n\n\n:::\n:::\n\n\n\n::: {.cell}\n\n```{.r .cell-code}\n# glimpse from dplyr\nglimpse(covid_data)\n```\n\n::: {.cell-output .cell-output-stdout}\n\n```\nRows: 102,245\nColumns: 16\n$ `Last update date`         <chr> \"06/24/2022\", \"06/24/2022\", \"06/24/2022\", \"…\n$ `Town number`              <dbl> 1, 2, 3, 4, 5, 6, 7, 8, 9, 10, 11, 12, 13, …\n$ Town                       <chr> \"Andover\", \"Ansonia\", \"Ashford\", \"Avon\", \"B…\n$ `Total cases`              <dbl> 514, 4911, 744, 3030, 527, 1306, 4098, 991,…\n$ `Confirmed cases`          <dbl> 439, 4222, 671, 2773, 490, 1163, 3751, 901,…\n$ `Probable cases`           <dbl> 75, 689, 73, 257, 37, 143, 347, 90, 745, 91…\n$ `Case rate`                <dbl> 15884, 26327, 17485, 16579, 14615, 20990, 2…\n$ `Total deaths`             <dbl> 6, 49, 5, 81, 8, 11, 52, 4, 71, 3, 136, 5, …\n$ `Confirmed deaths`         <dbl> 4, 39, 4, 65, 7, 11, 45, 3, 56, 2, 116, 4, …\n$ `Probable deaths`          <dbl> 2, 10, 1, 16, 1, 0, 7, 1, 15, 1, 20, 1, 0, …\n$ `People tested`            <dbl> 2442, 16305, 3398, 17103, 2698, 4909, 16527…\n$ `Rate tested per 100k`     <dbl> 75464, 87408, 79859, 93582, 74820, 78897, 8…\n$ `Number of tests`          <dbl> 9378, 77023, 13168, 74898, 11013, 23227, 75…\n$ `Number of positives`      <dbl> 590, 6048, 896, 3563, 621, 1591, 4960, 1211…\n$ `Number of negatives`      <dbl> 8780, 70818, 12259, 71253, 10378, 21591, 70…\n$ `Number of indeterminates` <dbl> 8, 157, 13, 82, 14, 45, 83, 31, 84, 22, 201…\n```\n\n\n:::\n:::\n\n\n\n::: {.callout-note}\nWorking with Excel files (`.xlsx`) is covered in [Working with Excel Files](../further-reading/excel-files.qmd).\n:::\n\n::: {.callout-note}\nWriting data to files — CSV, parquet, and others — is covered in\n[Writing Data Files](../further-reading/writing-files.qmd).\n:::\n",
    "supporting": [
      "index_files"
    ],
    "filters": [
      "rmarkdown/pagebreak.lua"
    ],
    "includes": {},
    "engineDependencies": {},
    "preserve": {},
    "postProcess": true
  }
}